LICENSE.md
README.md
setup.py
quick_trade/__init__.py
quick_trade/_code_inspect.py
quick_trade/_saving.py
quick_trade/brokers.py
quick_trade/indicators.py
quick_trade/plots.py
quick_trade/trading_sys.py
quick_trade/utils.py
quick_trade.egg-info/PKG-INFO
quick_trade.egg-info/SOURCES.txt
quick_trade.egg-info/dependency_links.txt
quick_trade.egg-info/requires.txt
quick_trade.egg-info/top_level.txt
quick_trade/tuner/__init__.py
quick_trade/tuner/core.py
quick_trade/tuner/tuner.py
quick_trade/tuner/avoid_overfitting/__init__.py
quick_trade/tuner/avoid_overfitting/validation_analysis.py
quick_trade/tuner/avoid_overfitting/volatility.py
quick_trade/tuner/avoid_overfitting/walkforward.py