Metadata-Version: 2.1
Name: quick-trade
Version: 7.9.6
Summary: Library for easy management and customization of algorithmic trading.
Download-URL: https://github.com/quick-trade/quick_trade/archive/7.9.6.tar.gz
Author: Vlad Kochetov
Author-email: vladyslavdrrragonkoch@gmail.com
License: cc-by-sa-4.0
Project-URL: Documentation, https://quick-trade.github.io/quick_trade/#/
Project-URL: Source, https://github.com/quick-trade/quick_trade
Project-URL: Twitter, https://twitter.com/quick_trade_tw
Project-URL: Bug Tracker, https://github.com/quick-trade/quick_trade/issues
Keywords: technical-analysis,python3,trading,trading-bot,trading,binance-trading,ccxt
Classifier: Intended Audience :: Financial and Insurance Industry
Classifier: Programming Language :: Python :: 3.6
Classifier: Programming Language :: Python :: 3.7
Classifier: Programming Language :: Python :: 3.8
Classifier: Programming Language :: Python :: 3.9
Classifier: Programming Language :: Python :: 3.10
Classifier: Programming Language :: Python :: 3
Requires-Python: >=3.0
License-File: LICENSE.md
